handy/__init__.py
handy/_handy.py
handy/decorators.py
handy/re_pattern.py
handy/re_tk.py
handy_utils-0.0.1a8.dist-info/LICENSE
handy_utils-0.0.1a8.dist-info/WHEEL
handy_utils-0.0.1a8.dist-info/METADATA
handy_utils-0.0.1a8.dist-info/RECORD
